LICENSE
MANIFEST.in
README.rst
setup.py
Ximpia.egg-info/PKG-INFO
Ximpia.egg-info/SOURCES.txt
Ximpia.egg-info/dependency_links.txt
Ximpia.egg-info/not-zip-safe
Ximpia.egg-info/requires.txt
Ximpia.egg-info/top_level.txt
docs/Makefile
docs/about.rst
docs/conf.py
docs/example.rst
docs/index.rst
docs/quickstart.rst
docs/_build/doctrees/about.doctree
docs/_build/doctrees/environment.pickle
docs/_build/doctrees/example.doctree
docs/_build/doctrees/index.doctree
docs/_build/doctrees/quickstart.doctree
docs/_build/doctrees/front-end/index.doctree
docs/_build/doctrees/front-end/visual-components/action.doctree
docs/_build/doctrees/front-end/visual-components/content.doctree
docs/_build/doctrees/front-end/visual-components/input.doctree
docs/_build/doctrees/front-end/visual-components/layout.doctree
docs/_build/doctrees/front-end/visual-components/list.doctree
docs/_build/doctrees/front-end/visual-components/media.doctree
docs/_build/doctrees/front-end/visual-components/window.doctree
docs/_build/doctrees/xpcore/business.doctree
docs/_build/doctrees/xpcore/commands.doctree
docs/_build/doctrees/xpcore/data.doctree
docs/_build/doctrees/xpcore/fields.doctree
docs/_build/doctrees/xpcore/index.doctree
docs/_build/doctrees/xpcore/models.doctree
docs/_build/doctrees/xpcore/service.doctree
docs/_build/doctrees/xpcore/workflow.doctree
docs/_build/doctrees/xpsite/index.doctree
docs/_build/doctrees/xpsite/models.doctree
docs/_build/html/.buildinfo
docs/_build/html/about.html
docs/_build/html/example.html
docs/_build/html/genindex.html
docs/_build/html/index.html
docs/_build/html/objects.inv
docs/_build/html/py-modindex.html
docs/_build/html/quickstart.html
docs/_build/html/search.html
docs/_build/html/searchindex.js
docs/_build/html/_images/data-list-low.png
docs/_build/html/_images/ximpia-app-low.png
docs/_build/html/_images/ximpia-app.png
docs/_build/html/_modules/index.html
docs/_build/html/_modules/ximpia/xpcore/business.html
docs/_build/html/_modules/ximpia/xpcore/models.html
docs/_build/html/_modules/ximpia/xpcore/service.html
docs/_build/html/_sources/about.txt
docs/_build/html/_sources/example.txt
docs/_build/html/_sources/index.txt
